Metadata-Version: 2.1
Name: dsnd-prob-vd
Version: 1.0
Summary: Gaussian and Binomial distributions
Home-page: UNKNOWN
Author: David Yacoub
Author-email: daveshtine2010@yahoo.com
License: UNKNOWN
Platform: UNKNOWN
